README.md
setup.py
qbane/__init__.py
qbane/bruteforcer.py
qbane/ddos.py
qbane/extrafun.py
qbane/hasher.py
qbane/infos.py
qbane/iot.py
qbane/pager.py
qbane/payloads.py
qbane/proxer.py
qbane/vulns.py
qbane/wp.py
qbane.egg-info/PKG-INFO
qbane.egg-info/SOURCES.txt
qbane.egg-info/dependency_links.txt
qbane.egg-info/requires.txt
qbane.egg-info/top_level.txt